InternetOfThings101IntelEdison/README.md
InternetOfThings101IntelEdison/__init__.py
InternetOfThings101IntelEdison/__main__.py
InternetOfThings101IntelEdison/file.epub
InternetOfThings101IntelEdison/index.html
InternetOfThings101IntelEdison/css/__init__.py
InternetOfThings101IntelEdison/css/annotations.css
InternetOfThings101IntelEdison/css/main.css
InternetOfThings101IntelEdison/css/normalize.css
InternetOfThings101IntelEdison/css/popup.css
InternetOfThings101IntelEdison/font/__init__.py
InternetOfThings101IntelEdison/font/fontello.eot
InternetOfThings101IntelEdison/font/fontello.svg
InternetOfThings101IntelEdison/font/fontello.ttf
InternetOfThings101IntelEdison/font/fontello.woff
InternetOfThings101IntelEdison/img/__init__.py
InternetOfThings101IntelEdison/img/annotator-glyph-sprite.png
InternetOfThings101IntelEdison/img/annotator-icon-sprite.png
InternetOfThings101IntelEdison/img/apple-touch-icon.png
InternetOfThings101IntelEdison/img/cancelfullscreen.png
InternetOfThings101IntelEdison/img/close.png
InternetOfThings101IntelEdison/img/fullscreen.png
InternetOfThings101IntelEdison/img/loader.gif
InternetOfThings101IntelEdison/img/menu-icon.png
InternetOfThings101IntelEdison/img/save.png
InternetOfThings101IntelEdison/img/saved.png
InternetOfThings101IntelEdison/img/settings-s.png
InternetOfThings101IntelEdison/img/settings.png
InternetOfThings101IntelEdison/img/star.png
InternetOfThings101IntelEdison/js/__init__.py
InternetOfThings101IntelEdison/js/epub.js
InternetOfThings101IntelEdison/js/epub.min.js
InternetOfThings101IntelEdison/js/epub.min.map
InternetOfThings101IntelEdison/js/hooks.min.js
InternetOfThings101IntelEdison/js/hooks.min.map
InternetOfThings101IntelEdison/js/reader.js
InternetOfThings101IntelEdison/js/reader.js.map
InternetOfThings101IntelEdison/js/reader.min.js
InternetOfThings101IntelEdison/js/reader.min.map
InternetOfThings101IntelEdison/js/hooks/__init__.py
InternetOfThings101IntelEdison/js/hooks/extensions/__init__.py
internet_of_things_101_intel_edison-2024.3.4.0.dist-info/METADATA
internet_of_things_101_intel_edison-2024.3.4.0.dist-info/WHEEL
internet_of_things_101_intel_edison-2024.3.4.0.dist-info/entry_points.txt
internet_of_things_101_intel_edison-2024.3.4.0.dist-info/top_level.txt
internet_of_things_101_intel_edison-2024.3.4.0.dist-info/RECORD
